{
  "survey_date": "2008-06-09",
  "survey_method": null,
  "survey_type": "Standard Survey",
  "fish_species": [
    {
      "species_name": "BRB",
      "count": 1,
      "length_stats": {
        "average": null,
        "minimum": null,
        "maximum": null
      },
      "weight_stats": {
        "average": 1.83,
        "total": 830.0,
        "quartile": "0.6-1.0"
      },
      "gear": "Standard gill nets",
      "cpue": 0.17
    },
    {
      "species_name": "BLC",
      "count": 5,
      "length_stats": {
        "average": null,
        "minimum": null,
        "maximum": null
      },
      "weight_stats": {
        "average": 0.27,
        "total": 607.0,
        "quartile": "0.2-0.5"
      },
      "gear": "Standard gill nets",
      "cpue": 0.83
    },
    {
      "species_name": "NOP",
      "count": 17,
      "length_stats": {
        "average": null,
        "minimum": null,
        "maximum": null
      },
      "weight_stats": {
        "average": 2.3,
        "total": 17706.0,
        "quartile": "1.6-2.9"
      },
      "gear": "Standard gill nets",
      "cpue": 2.83
    },
    {
      "species_name": "HSF",
      "count": 73,
      "length_stats": {
        "average": null,
        "minimum": null,
        "maximum": null
      },
      "weight_stats": {
        "average": 0.41,
        "total": 13656.0,
        "quartile": "N/A"
      },
      "gear": "Standard trap nets",
      "cpue": 8.11
    },
    {
      "species_name": "BLG",
      "count": 342,
      "length_stats": {
        "average": null,
        "minimum": null,
        "maximum": null
      },
      "weight_stats": {
        "average": 0.22,
        "total": 34109.0,
        "quartile": "0.1-0.3"
      },
      "gear": "Standard trap nets",
      "cpue": 38.0
    },
    {
      "species_name": "LMB",
      "count": 6,
      "length_stats": {
        "average": null,
        "minimum": null,
        "maximum": null
      },
      "weight_stats": {
        "average": 1.21,
        "total": 3283.0,
        "quartile": "0.2-0.7"
      },
      "gear": "Standard trap nets",
      "cpue": 0.67
    },
    {
      "species_name": "WAE",
      "count": 2,
      "length_stats": {
        "average": null,
        "minimum": null,
        "maximum": null
      },
      "weight_stats": {
        "average": 2.82,
        "total": 2560.0,
        "quartile": "1.3-2.5"
      },
      "gear": "Standard gill nets",
      "cpue": 0.33
    },
    {
      "species_name": "BRB",
      "count": 3,
      "length_stats": {
        "average": null,
        "minimum": null,
        "maximum": null
      },
      "weight_stats": {
        "average": 1.64,
        "total": 2232.0,
        "quartile": "0.6-1.1"
      },
      "gear": "Standard trap nets",
      "cpue": 0.33
    },
    {
      "species_name": "BLC",
      "count": 47,
      "length_stats": {
        "average": null,
        "minimum": null,
        "maximum": null
      },
      "weight_stats": {
        "average": 0.53,
        "total": 11355.0,
        "quartile": "0.2-0.6"
      },
      "gear": "Standard trap nets",
      "cpue": 5.22
    },
    {
      "species_name": "YEB",
      "count": 36,
      "length_stats": {
        "average": null,
        "minimum": null,
        "maximum": null
      },
      "weight_stats": {
        "average": 0.49,
        "total": 7939.0,
        "quartile": "0.4-0.8"
      },
      "gear": "Standard gill nets",
      "cpue": 6.0
    },
    {
      "species_name": "LMB",
      "count": 35,
      "length_stats": {
        "average": null,
        "minimum": null,
        "maximum": null
      },
      "weight_stats": {
        "average": 1.17,
        "total": 18552.0,
        "quartile": "N/A"
      },
      "gear": "Standard electrofishing",
      "cpue": 53.66
    },
    {
      "species_name": "HSF",
      "count": 2,
      "length_stats": {
        "average": null,
        "minimum": null,
        "maximum": null
      },
      "weight_stats": {
        "average": 0.43,
        "total": 387.0,
        "quartile": "N/A"
      },
      "gear": "Standard gill nets",
      "cpue": 0.33
    },
    {
      "species_name": "PMK",
      "count": 18,
      "length_stats": {
        "average": null,
        "minimum": null,
        "maximum": null
      },
      "weight_stats": {
        "average": 0.4,
        "total": 3243.0,
        "quartile": "0.1-0.2"
      },
      "gear": "Standard trap nets",
      "cpue": 2.0
    },
    {
      "species_name": "BLG",
      "count": 10,
      "length_stats": {
        "average": null,
        "minimum": null,
        "maximum": null
      },
      "weight_stats": {
        "average": 0.36,
        "total": 1645.0,
        "quartile": "N/A"
      },
      "gear": "Standard gill nets",
      "cpue": 1.67
    },
    {
      "species_name": "LMB",
      "count": 7,
      "length_stats": {
        "average": null,
        "minimum": null,
        "maximum": null
      },
      "weight_stats": {
        "average": 0.86,
        "total": 2742.0,
        "quartile": "0.6-1.2"
      },
      "gear": "Standard gill nets",
      "cpue": 1.17
    },
    {
      "species_name": "YEB",
      "count": 68,
      "length_stats": {
        "average": null,
        "minimum": null,
        "maximum": null
      },
      "weight_stats": {
        "average": 0.58,
        "total": 17917.0,
        "quartile": "0.5-0.8"
      },
      "gear": "Standard trap nets",
      "cpue": 7.56
    }
  ],
  "total_fish_caught": 672,
  "dowlknum": "56025200",
  "fetch_timestamp": 1757117037.9138885
}