{
  "survey_date": "2018-08-27",
  "survey_method": null,
  "survey_type": "Standard Survey",
  "fish_species": [
    {
      "species_name": "YEP",
      "count": 11,
      "length_stats": {
        "average": null,
        "minimum": null,
        "maximum": null
      },
      "weight_stats": {
        "average": 0.09,
        "total": 469.0,
        "quartile": "0.1-0.4"
      },
      "gear": "Standard trap nets",
      "cpue": 1.83
    },
    {
      "species_name": "YEB",
      "count": 29,
      "length_stats": {
        "average": null,
        "minimum": null,
        "maximum": null
      },
      "weight_stats": {
        "average": 0.93,
        "total": 12216.0,
        "quartile": "0.4-0.7"
      },
      "gear": "Standard gill nets",
      "cpue": 7.25
    },
    {
      "species_name": "NOP",
      "count": 50,
      "length_stats": {
        "average": null,
        "minimum": null,
        "maximum": null
      },
      "weight_stats": {
        "average": 2.17,
        "total": 49211.0,
        "quartile": "1.5-2.6"
      },
      "gear": "Standard gill nets",
      "cpue": 12.5
    },
    {
      "species_name": "YEB",
      "count": 6,
      "length_stats": {
        "average": null,
        "minimum": null,
        "maximum": null
      },
      "weight_stats": {
        "average": 0.79,
        "total": 2152.0,
        "quartile": "N/A"
      },
      "gear": "Special trap nets",
      "cpue": 1.0
    },
    {
      "species_name": "NOP",
      "count": 8,
      "length_stats": {
        "average": null,
        "minimum": null,
        "maximum": null
      },
      "weight_stats": {
        "average": 3.77,
        "total": 13679.0,
        "quartile": "N/A"
      },
      "gear": "Special trap nets",
      "cpue": 1.33
    },
    {
      "species_name": "GOS",
      "count": 7,
      "length_stats": {
        "average": null,
        "minimum": null,
        "maximum": null
      },
      "weight_stats": {
        "average": 0.1,
        "total": 321.0,
        "quartile": "0.1-0.1"
      },
      "gear": "Standard gill nets",
      "cpue": 1.75
    },
    {
      "species_name": "GOS",
      "count": 2,
      "length_stats": {
        "average": null,
        "minimum": null,
        "maximum": null
      },
      "weight_stats": {
        "average": 0.04,
        "total": 32.0,
        "quartile": "N/A"
      },
      "gear": "Special trap nets",
      "cpue": 0.33
    },
    {
      "species_name": "CAP",
      "count": 4,
      "length_stats": {
        "average": null,
        "minimum": null,
        "maximum": null
      },
      "weight_stats": {
        "average": 1.73,
        "total": 3137.0,
        "quartile": "2.3-6.0"
      },
      "gear": "Standard gill nets",
      "cpue": 1.0
    },
    {
      "species_name": "CAP",
      "count": 4,
      "length_stats": {
        "average": null,
        "minimum": null,
        "maximum": null
      },
      "weight_stats": {
        "average": 6.9,
        "total": 12516.0,
        "quartile": "N/A"
      },
      "gear": "Special trap nets",
      "cpue": 0.67
    },
    {
      "species_name": "NOP",
      "count": 1,
      "length_stats": {
        "average": null,
        "minimum": null,
        "maximum": null
      },
      "weight_stats": {
        "average": 4.41,
        "total": 2000.0,
        "quartile": "N/A"
      },
      "gear": "Standard trap nets",
      "cpue": 0.17
    },
    {
      "species_name": "HSF",
      "count": 1,
      "length_stats": {
        "average": null,
        "minimum": null,
        "maximum": null
      },
      "weight_stats": {
        "average": 0.03,
        "total": 15.0,
        "quartile": "N/A"
      },
      "gear": "Standard gill nets",
      "cpue": 0.25
    },
    {
      "species_name": "SHR",
      "count": 3,
      "length_stats": {
        "average": null,
        "minimum": null,
        "maximum": null
      },
      "weight_stats": {
        "average": 1.01,
        "total": 1378.0,
        "quartile": "1.3-2.0"
      },
      "gear": "Standard gill nets",
      "cpue": 0.75
    },
    {
      "species_name": "CAP",
      "count": 6,
      "length_stats": {
        "average": null,
        "minimum": null,
        "maximum": null
      },
      "weight_stats": {
        "average": 3.51,
        "total": 9561.0,
        "quartile": "3.3-6.8"
      },
      "gear": "Standard trap nets",
      "cpue": 1.0
    },
    {
      "species_name": "WAE",
      "count": 32,
      "length_stats": {
        "average": null,
        "minimum": null,
        "maximum": null
      },
      "weight_stats": {
        "average": 2.47,
        "total": 35830.0,
        "quartile": "1.3-2.5"
      },
      "gear": "Standard gill nets",
      "cpue": 8.0
    },
    {
      "species_name": "WAE",
      "count": 1,
      "length_stats": {
        "average": null,
        "minimum": null,
        "maximum": null
      },
      "weight_stats": {
        "average": 2.31,
        "total": 1048.0,
        "quartile": "N/A"
      },
      "gear": "Special trap nets",
      "cpue": 0.17
    },
    {
      "species_name": "BLG",
      "count": 2,
      "length_stats": {
        "average": null,
        "minimum": null,
        "maximum": null
      },
      "weight_stats": {
        "average": 0.4,
        "total": 367.0,
        "quartile": "N/A"
      },
      "gear": "Standard gill nets",
      "cpue": 0.5
    },
    {
      "species_name": "PMK",
      "count": 1,
      "length_stats": {
        "average": null,
        "minimum": null,
        "maximum": null
      },
      "weight_stats": {
        "average": 0.05,
        "total": 22.0,
        "quartile": "N/A"
      },
      "gear": "Standard gill nets",
      "cpue": 0.25
    },
    {
      "species_name": "BLG",
      "count": 40,
      "length_stats": {
        "average": null,
        "minimum": null,
        "maximum": null
      },
      "weight_stats": {
        "average": 0.34,
        "total": 6108.0,
        "quartile": "N/A"
      },
      "gear": "Special trap nets",
      "cpue": 6.67
    },
    {
      "species_name": "BOF",
      "count": 3,
      "length_stats": {
        "average": null,
        "minimum": null,
        "maximum": null
      },
      "weight_stats": {
        "average": 4.38,
        "total": 5967.0,
        "quartile": "3.4-4.5"
      },
      "gear": "Standard gill nets",
      "cpue": 0.75
    },
    {
      "species_name": "BOF",
      "count": 1,
      "length_stats": {
        "average": null,
        "minimum": null,
        "maximum": null
      },
      "weight_stats": {
        "average": 4.89,
        "total": 2216.0,
        "quartile": "N/A"
      },
      "gear": "Special trap nets",
      "cpue": 0.17
    },
    {
      "species_name": "WTS",
      "count": 28,
      "length_stats": {
        "average": null,
        "minimum": null,
        "maximum": null
      },
      "weight_stats": {
        "average": 1.95,
        "total": 24779.0,
        "quartile": "1.6-2.3"
      },
      "gear": "Standard gill nets",
      "cpue": 7.0
    },
    {
      "species_name": "BLC",
      "count": 77,
      "length_stats": {
        "average": null,
        "minimum": null,
        "maximum": null
      },
      "weight_stats": {
        "average": 0.25,
        "total": 8882.0,
        "quartile": "0.2-0.4"
      },
      "gear": "Standard gill nets",
      "cpue": 19.25
    },
    {
      "species_name": "BLB",
      "count": 6,
      "length_stats": {
        "average": null,
        "minimum": null,
        "maximum": null
      },
      "weight_stats": {
        "average": 0.63,
        "total": 1710.0,
        "quartile": "0.2-0.6"
      },
      "gear": "Standard gill nets",
      "cpue": 1.5
    },
    {
      "species_name": "WTS",
      "count": 2,
      "length_stats": {
        "average": null,
        "minimum": null,
        "maximum": null
      },
      "weight_stats": {
        "average": 2.53,
        "total": 2291.0,
        "quartile": "N/A"
      },
      "gear": "Special trap nets",
      "cpue": 0.33
    },
    {
      "species_name": "BLC",
      "count": 206,
      "length_stats": {
        "average": null,
        "minimum": null,
        "maximum": null
      },
      "weight_stats": {
        "average": 0.52,
        "total": 48718.0,
        "quartile": "N/A"
      },
      "gear": "Special trap nets",
      "cpue": 34.33
    },
    {
      "species_name": "YEP",
      "count": 43,
      "length_stats": {
        "average": null,
        "minimum": null,
        "maximum": null
      },
      "weight_stats": {
        "average": 0.1,
        "total": 2021.0,
        "quartile": "0.1-0.2"
      },
      "gear": "Standard gill nets",
      "cpue": 10.75
    },
    {
      "species_name": "BLB",
      "count": 1,
      "length_stats": {
        "average": null,
        "minimum": null,
        "maximum": null
      },
      "weight_stats": {
        "average": 0.33,
        "total": 151.0,
        "quartile": "N/A"
      },
      "gear": "Special trap nets",
      "cpue": 0.17
    },
    {
      "species_name": "WAE",
      "count": 1,
      "length_stats": {
        "average": null,
        "minimum": null,
        "maximum": null
      },
      "weight_stats": {
        "average": 2.43,
        "total": 1104.0,
        "quartile": "1.2-3.0"
      },
      "gear": "Standard trap nets",
      "cpue": 0.17
    },
    {
      "species_name": "BRB",
      "count": 1,
      "length_stats": {
        "average": null,
        "minimum": null,
        "maximum": null
      },
      "weight_stats": {
        "average": 1.11,
        "total": 502.0,
        "quartile": "N/A"
      },
      "gear": "Special trap nets",
      "cpue": 0.17
    },
    {
      "species_name": "YEP",
      "count": 27,
      "length_stats": {
        "average": null,
        "minimum": null,
        "maximum": null
      },
      "weight_stats": {
        "average": 0.08,
        "total": 971.0,
        "quartile": "N/A"
      },
      "gear": "Special trap nets",
      "cpue": 4.5
    },
    {
      "species_name": "BLG",
      "count": 27,
      "length_stats": {
        "average": null,
        "minimum": null,
        "maximum": null
      },
      "weight_stats": {
        "average": 0.38,
        "total": 4684.0,
        "quartile": "0.1-0.5"
      },
      "gear": "Standard trap nets",
      "cpue": 4.5
    },
    {
      "species_name": "PMK",
      "count": 2,
      "length_stats": {
        "average": null,
        "minimum": null,
        "maximum": null
      },
      "weight_stats": {
        "average": 0.05,
        "total": 41.0,
        "quartile": "0.1-0.3"
      },
      "gear": "Standard trap nets",
      "cpue": 0.33
    },
    {
      "species_name": "BOF",
      "count": 1,
      "length_stats": {
        "average": null,
        "minimum": null,
        "maximum": null
      },
      "weight_stats": {
        "average": 4.24,
        "total": 1923.0,
        "quartile": "2.1-4.3"
      },
      "gear": "Standard trap nets",
      "cpue": 0.17
    },
    {
      "species_name": "WTS",
      "count": 4,
      "length_stats": {
        "average": null,
        "minimum": null,
        "maximum": null
      },
      "weight_stats": {
        "average": 2.6,
        "total": 4719.0,
        "quartile": "1.5-2.6"
      },
      "gear": "Standard trap nets",
      "cpue": 0.67
    },
    {
      "species_name": "BLC",
      "count": 62,
      "length_stats": {
        "average": null,
        "minimum": null,
        "maximum": null
      },
      "weight_stats": {
        "average": 0.4,
        "total": 11188.0,
        "quartile": "0.2-0.6"
      },
      "gear": "Standard trap nets",
      "cpue": 10.33
    }
  ],
  "total_fish_caught": 700,
  "dowlknum": "77018200",
  "fetch_timestamp": 1757117028.567502
}