{
  "survey_date": "2017-07-24",
  "survey_method": null,
  "survey_type": "Standard Survey",
  "fish_species": [
    {
      "species_name": "BRB",
      "count": 1,
      "length_stats": {
        "average": null,
        "minimum": null,
        "maximum": null
      },
      "weight_stats": {
        "average": 0.98,
        "total": 446.0,
        "quartile": "0.5-1.0"
      },
      "gear": "Standard trap nets",
      "cpue": 0.11
    },
    {
      "species_name": "YEP",
      "count": 1,
      "length_stats": {
        "average": null,
        "minimum": null,
        "maximum": null
      },
      "weight_stats": {
        "average": 0.25,
        "total": 112.0,
        "quartile": "0.1-0.2"
      },
      "gear": "Standard trap nets",
      "cpue": 0.11
    },
    {
      "species_name": "GSF",
      "count": 4,
      "length_stats": {
        "average": null,
        "minimum": null,
        "maximum": null
      },
      "weight_stats": {
        "average": 0.03,
        "total": 50.0,
        "quartile": "0.1-0.2"
      },
      "gear": "Standard trap nets",
      "cpue": 0.44
    },
    {
      "species_name": "YEB",
      "count": 40,
      "length_stats": {
        "average": null,
        "minimum": null,
        "maximum": null
      },
      "weight_stats": {
        "average": 0.55,
        "total": 9999.0,
        "quartile": "0.5-0.8"
      },
      "gear": "Standard gill nets",
      "cpue": 6.67
    },
    {
      "species_name": "NOP",
      "count": 30,
      "length_stats": {
        "average": null,
        "minimum": null,
        "maximum": null
      },
      "weight_stats": {
        "average": 1.56,
        "total": 21170.0,
        "quartile": "2.0-3.5"
      },
      "gear": "Standard gill nets",
      "cpue": 5.0
    },
    {
      "species_name": "LMB",
      "count": 66,
      "length_stats": {
        "average": null,
        "minimum": null,
        "maximum": null
      },
      "weight_stats": {
        "average": 1.34,
        "total": 40233.0,
        "quartile": "N/A"
      },
      "gear": "Standard electrofishing",
      "cpue": 32.98
    },
    {
      "species_name": "YEB",
      "count": 34,
      "length_stats": {
        "average": null,
        "minimum": null,
        "maximum": null
      },
      "weight_stats": {
        "average": 0.48,
        "total": 7432.0,
        "quartile": "0.5-0.8"
      },
      "gear": "Standard trap nets",
      "cpue": 3.78
    },
    {
      "species_name": "NOP",
      "count": 5,
      "length_stats": {
        "average": null,
        "minimum": null,
        "maximum": null
      },
      "weight_stats": {
        "average": 0.8,
        "total": 1821.0,
        "quartile": "N/A"
      },
      "gear": "Standard trap nets",
      "cpue": 0.56
    },
    {
      "species_name": "HSF",
      "count": 5,
      "length_stats": {
        "average": null,
        "minimum": null,
        "maximum": null
      },
      "weight_stats": {
        "average": 0.17,
        "total": 396.0,
        "quartile": "N/A"
      },
      "gear": "Standard gill nets",
      "cpue": 0.83
    },
    {
      "species_name": "HSF",
      "count": 38,
      "length_stats": {
        "average": null,
        "minimum": null,
        "maximum": null
      },
      "weight_stats": {
        "average": 0.27,
        "total": 4722.0,
        "quartile": "N/A"
      },
      "gear": "Standard trap nets",
      "cpue": 4.22
    },
    {
      "species_name": "LMB",
      "count": 2,
      "length_stats": {
        "average": null,
        "minimum": null,
        "maximum": null
      },
      "weight_stats": {
        "average": 0.52,
        "total": 468.0,
        "quartile": "0.4-1.0"
      },
      "gear": "Standard gill nets",
      "cpue": 0.33
    },
    {
      "species_name": "BLG",
      "count": 22,
      "length_stats": {
        "average": null,
        "minimum": null,
        "maximum": null
      },
      "weight_stats": {
        "average": 0.1,
        "total": 980.0,
        "quartile": "N/A"
      },
      "gear": "Standard gill nets",
      "cpue": 3.67
    },
    {
      "species_name": "PMK",
      "count": 3,
      "length_stats": {
        "average": null,
        "minimum": null,
        "maximum": null
      },
      "weight_stats": {
        "average": 0.11,
        "total": 145.0,
        "quartile": "N/A"
      },
      "gear": "Standard gill nets",
      "cpue": 0.5
    },
    {
      "species_name": "BLC",
      "count": 15,
      "length_stats": {
        "average": null,
        "minimum": null,
        "maximum": null
      },
      "weight_stats": {
        "average": 0.24,
        "total": 1665.0,
        "quartile": "0.1-0.3"
      },
      "gear": "Standard gill nets",
      "cpue": 2.5
    },
    {
      "species_name": "GSF",
      "count": 1,
      "length_stats": {
        "average": null,
        "minimum": null,
        "maximum": null
      },
      "weight_stats": {
        "average": 0.04,
        "total": 16.0,
        "quartile": "N/A"
      },
      "gear": "Standard gill nets",
      "cpue": 0.17
    },
    {
      "species_name": "LMB",
      "count": 5,
      "length_stats": {
        "average": null,
        "minimum": null,
        "maximum": null
      },
      "weight_stats": {
        "average": 0.28,
        "total": 641.0,
        "quartile": "0.2-0.9"
      },
      "gear": "Standard trap nets",
      "cpue": 0.56
    },
    {
      "species_name": "PMK",
      "count": 21,
      "length_stats": {
        "average": null,
        "minimum": null,
        "maximum": null
      },
      "weight_stats": {
        "average": 0.14,
        "total": 1362.0,
        "quartile": "0.1-0.2"
      },
      "gear": "Standard trap nets",
      "cpue": 2.33
    },
    {
      "species_name": "BLG",
      "count": 73,
      "length_stats": {
        "average": null,
        "minimum": null,
        "maximum": null
      },
      "weight_stats": {
        "average": 0.13,
        "total": 4255.0,
        "quartile": "0.1-0.3"
      },
      "gear": "Standard trap nets",
      "cpue": 8.11
    },
    {
      "species_name": "BLC",
      "count": 12,
      "length_stats": {
        "average": null,
        "minimum": null,
        "maximum": null
      },
      "weight_stats": {
        "average": 0.41,
        "total": 2256.0,
        "quartile": "0.2-0.3"
      },
      "gear": "Standard trap nets",
      "cpue": 1.33
    }
  ],
  "total_fish_caught": 378,
  "dowlknum": "86001100",
  "fetch_timestamp": 1757117073.409271
}