{
  "survey_date": "2022-08-15",
  "survey_method": null,
  "survey_type": "Standard Survey",
  "fish_species": [
    {
      "species_name": "YEB",
      "count": 75,
      "length_stats": {
        "average": null,
        "minimum": null,
        "maximum": null
      },
      "weight_stats": {
        "average": 0.76,
        "total": 25913.0,
        "quartile": "0.4-0.7"
      },
      "gear": "Standard gill nets",
      "cpue": 25.0
    },
    {
      "species_name": "NOP",
      "count": 29,
      "length_stats": {
        "average": null,
        "minimum": null,
        "maximum": null
      },
      "weight_stats": {
        "average": 2.3,
        "total": 30264.0,
        "quartile": "1.8-3.3"
      },
      "gear": "Standard gill nets",
      "cpue": 9.67
    },
    {
      "species_name": "GOS",
      "count": 14,
      "length_stats": {
        "average": null,
        "minimum": null,
        "maximum": null
      },
      "weight_stats": {
        "average": 0.08,
        "total": 515.0,
        "quartile": "0.1-0.1"
      },
      "gear": "Standard gill nets",
      "cpue": 4.67
    },
    {
      "species_name": "LMB",
      "count": 32,
      "length_stats": {
        "average": null,
        "minimum": null,
        "maximum": null
      },
      "weight_stats": {
        "average": 2.03,
        "total": 29494.0,
        "quartile": "N/A"
      },
      "gear": "Standard electrofishing",
      "cpue": 36.19
    },
    {
      "species_name": "YEB",
      "count": 49,
      "length_stats": {
        "average": null,
        "minimum": null,
        "maximum": null
      },
      "weight_stats": {
        "average": 0.86,
        "total": 19154.0,
        "quartile": "0.4-0.7"
      },
      "gear": "Standard trap nets",
      "cpue": 5.44
    },
    {
      "species_name": "NOP",
      "count": 1,
      "length_stats": {
        "average": null,
        "minimum": null,
        "maximum": null
      },
      "weight_stats": {
        "average": 2.39,
        "total": 1084.0,
        "quartile": "N/A"
      },
      "gear": "Standard trap nets",
      "cpue": 0.11
    },
    {
      "species_name": "CAP",
      "count": 1,
      "length_stats": {
        "average": null,
        "minimum": null,
        "maximum": null
      },
      "weight_stats": {
        "average": 17.18,
        "total": 7794.0,
        "quartile": "2.0-4.5"
      },
      "gear": "Standard trap nets",
      "cpue": 0.11
    },
    {
      "species_name": "HSF",
      "count": 26,
      "length_stats": {
        "average": null,
        "minimum": null,
        "maximum": null
      },
      "weight_stats": {
        "average": 0.28,
        "total": 3293.0,
        "quartile": "N/A"
      },
      "gear": "Standard trap nets",
      "cpue": 2.89
    },
    {
      "species_name": "LMB",
      "count": 2,
      "length_stats": {
        "average": null,
        "minimum": null,
        "maximum": null
      },
      "weight_stats": {
        "average": 0.03,
        "total": 30.0,
        "quartile": "0.4-1.5"
      },
      "gear": "Standard gill nets",
      "cpue": 0.67
    },
    {
      "species_name": "BLG",
      "count": 40,
      "length_stats": {
        "average": null,
        "minimum": null,
        "maximum": null
      },
      "weight_stats": {
        "average": 0.09,
        "total": 1722.0,
        "quartile": "N/A"
      },
      "gear": "Standard gill nets",
      "cpue": 13.33
    },
    {
      "species_name": "PMK",
      "count": 5,
      "length_stats": {
        "average": null,
        "minimum": null,
        "maximum": null
      },
      "weight_stats": {
        "average": 0.19,
        "total": 427.0,
        "quartile": "N/A"
      },
      "gear": "Standard gill nets",
      "cpue": 1.67
    },
    {
      "species_name": "BOF",
      "count": 1,
      "length_stats": {
        "average": null,
        "minimum": null,
        "maximum": null
      },
      "weight_stats": {
        "average": 2.99,
        "total": 1354.0,
        "quartile": "1.9-3.3"
      },
      "gear": "Standard gill nets",
      "cpue": 0.33
    },
    {
      "species_name": "BLC",
      "count": 28,
      "length_stats": {
        "average": null,
        "minimum": null,
        "maximum": null
      },
      "weight_stats": {
        "average": 0.13,
        "total": 1676.0,
        "quartile": "0.1-0.3"
      },
      "gear": "Standard gill nets",
      "cpue": 9.33
    },
    {
      "species_name": "BLB",
      "count": 4,
      "length_stats": {
        "average": null,
        "minimum": null,
        "maximum": null
      },
      "weight_stats": {
        "average": 1.18,
        "total": 2140.0,
        "quartile": "0.2-0.5"
      },
      "gear": "Standard gill nets",
      "cpue": 1.33
    },
    {
      "species_name": "BRB",
      "count": 1,
      "length_stats": {
        "average": null,
        "minimum": null,
        "maximum": null
      },
      "weight_stats": {
        "average": 1.75,
        "total": 795.0,
        "quartile": "0.2-0.6"
      },
      "gear": "Standard gill nets",
      "cpue": 0.33
    },
    {
      "species_name": "PMK",
      "count": 27,
      "length_stats": {
        "average": null,
        "minimum": null,
        "maximum": null
      },
      "weight_stats": {
        "average": 0.14,
        "total": 1696.0,
        "quartile": "0.1-0.2"
      },
      "gear": "Standard trap nets",
      "cpue": 3.0
    },
    {
      "species_name": "BLG",
      "count": 412,
      "length_stats": {
        "average": null,
        "minimum": null,
        "maximum": null
      },
      "weight_stats": {
        "average": 0.15,
        "total": 28683.0,
        "quartile": "0.1-0.2"
      },
      "gear": "Standard trap nets",
      "cpue": 45.78
    },
    {
      "species_name": "BOF",
      "count": 1,
      "length_stats": {
        "average": null,
        "minimum": null,
        "maximum": null
      },
      "weight_stats": {
        "average": 5.19,
        "total": 2356.0,
        "quartile": "2.2-4.0"
      },
      "gear": "Standard trap nets",
      "cpue": 0.11
    },
    {
      "species_name": "BLC",
      "count": 22,
      "length_stats": {
        "average": null,
        "minimum": null,
        "maximum": null
      },
      "weight_stats": {
        "average": 0.24,
        "total": 2358.0,
        "quartile": "0.2-0.3"
      },
      "gear": "Standard trap nets",
      "cpue": 2.44
    }
  ],
  "total_fish_caught": 770,
  "dowlknum": "86017800",
  "fetch_timestamp": 1757117084.307973
}