{
  "survey_date": "2017-07-17",
  "survey_method": null,
  "survey_type": "Standard Survey",
  "fish_species": [
    {
      "species_name": "BRB",
      "count": 6,
      "length_stats": {
        "average": null,
        "minimum": null,
        "maximum": null
      },
      "weight_stats": {
        "average": 1.19,
        "total": 3232.0,
        "quartile": "0.7-1.1"
      },
      "gear": "Standard trap nets",
      "cpue": 0.55
    },
    {
      "species_name": "YEP",
      "count": 61,
      "length_stats": {
        "average": null,
        "minimum": null,
        "maximum": null
      },
      "weight_stats": {
        "average": 0.12,
        "total": 3366.0,
        "quartile": "0.1-0.2"
      },
      "gear": "Standard trap nets",
      "cpue": 5.55
    },
    {
      "species_name": "YEB",
      "count": 16,
      "length_stats": {
        "average": null,
        "minimum": null,
        "maximum": null
      },
      "weight_stats": {
        "average": 0.82,
        "total": 5960.0,
        "quartile": "0.6-0.9"
      },
      "gear": "Standard gill nets",
      "cpue": 1.33
    },
    {
      "species_name": "NOP",
      "count": 16,
      "length_stats": {
        "average": null,
        "minimum": null,
        "maximum": null
      },
      "weight_stats": {
        "average": 3.45,
        "total": 25024.0,
        "quartile": "1.6-2.8"
      },
      "gear": "Standard gill nets",
      "cpue": 1.33
    },
    {
      "species_name": "WAE",
      "count": 66,
      "length_stats": {
        "average": null,
        "minimum": null,
        "maximum": null
      },
      "weight_stats": {
        "average": 0.0,
        "total": 0.0,
        "quartile": "N/A"
      },
      "gear": "Fall electrofishing",
      "cpue": 108.34
    },
    {
      "species_name": "CAP",
      "count": 2,
      "length_stats": {
        "average": null,
        "minimum": null,
        "maximum": null
      },
      "weight_stats": {
        "average": 12.93,
        "total": 11726.0,
        "quartile": "2.3-8.2"
      },
      "gear": "Standard gill nets",
      "cpue": 0.17
    },
    {
      "species_name": "YEB",
      "count": 37,
      "length_stats": {
        "average": null,
        "minimum": null,
        "maximum": null
      },
      "weight_stats": {
        "average": 0.91,
        "total": 15349.0,
        "quartile": "0.6-0.9"
      },
      "gear": "Standard trap nets",
      "cpue": 3.36
    },
    {
      "species_name": "NOP",
      "count": 4,
      "length_stats": {
        "average": null,
        "minimum": null,
        "maximum": null
      },
      "weight_stats": {
        "average": 3.29,
        "total": 5968.0,
        "quartile": "N/A"
      },
      "gear": "Standard trap nets",
      "cpue": 0.36
    },
    {
      "species_name": "TRP",
      "count": 1,
      "length_stats": {
        "average": null,
        "minimum": null,
        "maximum": null
      },
      "weight_stats": {
        "average": 0.01,
        "total": 4.0,
        "quartile": "N/A"
      },
      "gear": "Standard gill nets",
      "cpue": 0.08
    },
    {
      "species_name": "SHR",
      "count": 1,
      "length_stats": {
        "average": null,
        "minimum": null,
        "maximum": null
      },
      "weight_stats": {
        "average": 0.75,
        "total": 341.0,
        "quartile": "1.1-2.2"
      },
      "gear": "Standard gill nets",
      "cpue": 0.08
    },
    {
      "species_name": "CAP",
      "count": 3,
      "length_stats": {
        "average": null,
        "minimum": null,
        "maximum": null
      },
      "weight_stats": {
        "average": 7.31,
        "total": 9946.0,
        "quartile": "3.8-8.7"
      },
      "gear": "Standard trap nets",
      "cpue": 0.27
    },
    {
      "species_name": "RKB",
      "count": 9,
      "length_stats": {
        "average": null,
        "minimum": null,
        "maximum": null
      },
      "weight_stats": {
        "average": 0.44,
        "total": 1815.0,
        "quartile": "0.3-0.5"
      },
      "gear": "Standard trap nets",
      "cpue": 0.82
    },
    {
      "species_name": "WAE",
      "count": 220,
      "length_stats": {
        "average": null,
        "minimum": null,
        "maximum": null
      },
      "weight_stats": {
        "average": 1.0,
        "total": 99604.0,
        "quartile": "1.2-2.1"
      },
      "gear": "Standard gill nets",
      "cpue": 18.33
    },
    {
      "species_name": "LKS",
      "count": 2,
      "length_stats": {
        "average": null,
        "minimum": null,
        "maximum": null
      },
      "weight_stats": {
        "average": 1.1,
        "total": 999.0,
        "quartile": "N/A"
      },
      "gear": "Standard gill nets",
      "cpue": 0.17
    },
    {
      "species_name": "HSF",
      "count": 1,
      "length_stats": {
        "average": null,
        "minimum": null,
        "maximum": null
      },
      "weight_stats": {
        "average": 0.24,
        "total": 111.0,
        "quartile": "N/A"
      },
      "gear": "Standard trap nets",
      "cpue": 0.09
    },
    {
      "species_name": "PMK",
      "count": 1,
      "length_stats": {
        "average": null,
        "minimum": null,
        "maximum": null
      },
      "weight_stats": {
        "average": 0.25,
        "total": 115.0,
        "quartile": "N/A"
      },
      "gear": "Standard gill nets",
      "cpue": 0.08
    },
    {
      "species_name": "SHR",
      "count": 3,
      "length_stats": {
        "average": null,
        "minimum": null,
        "maximum": null
      },
      "weight_stats": {
        "average": 2.06,
        "total": 2802.0,
        "quartile": "1.6-3.0"
      },
      "gear": "Standard trap nets",
      "cpue": 0.27
    },
    {
      "species_name": "TLC",
      "count": 26,
      "length_stats": {
        "average": null,
        "minimum": null,
        "maximum": null
      },
      "weight_stats": {
        "average": 0.54,
        "total": 6415.0,
        "quartile": "0.6-1.4"
      },
      "gear": "Standard gill nets",
      "cpue": 2.17
    },
    {
      "species_name": "WTS",
      "count": 101,
      "length_stats": {
        "average": null,
        "minimum": null,
        "maximum": null
      },
      "weight_stats": {
        "average": 1.07,
        "total": 49236.0,
        "quartile": "1.6-2.4"
      },
      "gear": "Standard gill nets",
      "cpue": 8.42
    },
    {
      "species_name": "BLC",
      "count": 9,
      "length_stats": {
        "average": null,
        "minimum": null,
        "maximum": null
      },
      "weight_stats": {
        "average": 0.24,
        "total": 965.0,
        "quartile": "0.3-0.6"
      },
      "gear": "Standard gill nets",
      "cpue": 0.75
    },
    {
      "species_name": "YEP",
      "count": 279,
      "length_stats": {
        "average": null,
        "minimum": null,
        "maximum": null
      },
      "weight_stats": {
        "average": 0.15,
        "total": 19597.0,
        "quartile": "0.1-0.2"
      },
      "gear": "Standard gill nets",
      "cpue": 23.25
    },
    {
      "species_name": "BRB",
      "count": 1,
      "length_stats": {
        "average": null,
        "minimum": null,
        "maximum": null
      },
      "weight_stats": {
        "average": 0.94,
        "total": 425.0,
        "quartile": "0.7-1.2"
      },
      "gear": "Standard gill nets",
      "cpue": 0.08
    },
    {
      "species_name": "WAE",
      "count": 10,
      "length_stats": {
        "average": null,
        "minimum": null,
        "maximum": null
      },
      "weight_stats": {
        "average": 3.53,
        "total": 16020.0,
        "quartile": "1.0-2.7"
      },
      "gear": "Standard trap nets",
      "cpue": 0.91
    },
    {
      "species_name": "LMB",
      "count": 9,
      "length_stats": {
        "average": null,
        "minimum": null,
        "maximum": null
      },
      "weight_stats": {
        "average": 0.65,
        "total": 2638.0,
        "quartile": "0.2-0.8"
      },
      "gear": "Standard trap nets",
      "cpue": 0.82
    },
    {
      "species_name": "BLG",
      "count": 255,
      "length_stats": {
        "average": null,
        "minimum": null,
        "maximum": null
      },
      "weight_stats": {
        "average": 0.12,
        "total": 13936.0,
        "quartile": "0.1-0.2"
      },
      "gear": "Standard trap nets",
      "cpue": 23.18
    },
    {
      "species_name": "PMK",
      "count": 187,
      "length_stats": {
        "average": null,
        "minimum": null,
        "maximum": null
      },
      "weight_stats": {
        "average": 0.15,
        "total": 13087.0,
        "quartile": "0.1-0.3"
      },
      "gear": "Standard trap nets",
      "cpue": 17.0
    },
    {
      "species_name": "BOF",
      "count": 10,
      "length_stats": {
        "average": null,
        "minimum": null,
        "maximum": null
      },
      "weight_stats": {
        "average": 5.49,
        "total": 24913.0,
        "quartile": "3.7-5.1"
      },
      "gear": "Standard trap nets",
      "cpue": 0.91
    },
    {
      "species_name": "WTS",
      "count": 26,
      "length_stats": {
        "average": null,
        "minimum": null,
        "maximum": null
      },
      "weight_stats": {
        "average": 2.48,
        "total": 29189.0,
        "quartile": "1.8-3.0"
      },
      "gear": "Standard trap nets",
      "cpue": 2.36
    },
    {
      "species_name": "BLC",
      "count": 9,
      "length_stats": {
        "average": null,
        "minimum": null,
        "maximum": null
      },
      "weight_stats": {
        "average": 0.13,
        "total": 548.0,
        "quartile": "0.3-0.6"
      },
      "gear": "Standard trap nets",
      "cpue": 0.82
    },
    {
      "species_name": "FRD",
      "count": 25,
      "length_stats": {
        "average": null,
        "minimum": null,
        "maximum": null
      },
      "weight_stats": {
        "average": 0.84,
        "total": 9552.0,
        "quartile": "0.2-0.8"
      },
      "gear": "Standard gill nets",
      "cpue": 2.08
    }
  ],
  "total_fish_caught": 1396,
  "dowlknum": "56013000",
  "fetch_timestamp": 1757117066.6327975
}