{
  "survey_date": "2008-08-18",
  "survey_method": null,
  "survey_type": "Standard Survey",
  "fish_species": [
    {
      "species_name": "NOP",
      "count": 4,
      "length_stats": {
        "average": null,
        "minimum": null,
        "maximum": null
      },
      "weight_stats": {
        "average": 3.29,
        "total": 5973.0,
        "quartile": "1.6-2.9"
      },
      "gear": "Standard gill nets",
      "cpue": 2.0
    },
    {
      "species_name": "LGP",
      "count": 1,
      "length_stats": {
        "average": null,
        "minimum": null,
        "maximum": null
      },
      "weight_stats": {
        "average": 0.0,
        "total": 0.0,
        "quartile": "N/A"
      },
      "gear": "Survey seining",
      "cpue": 0.5
    },
    {
      "species_name": "SMB",
      "count": 2,
      "length_stats": {
        "average": null,
        "minimum": null,
        "maximum": null
      },
      "weight_stats": {
        "average": 1.4,
        "total": 1274.0,
        "quartile": "N/A"
      },
      "gear": "Standard electrofishing",
      "cpue": 3.37
    },
    {
      "species_name": "CCF",
      "count": 4,
      "length_stats": {
        "average": null,
        "minimum": null,
        "maximum": null
      },
      "weight_stats": {
        "average": 4.8,
        "total": 8700.0,
        "quartile": "N/A"
      },
      "gear": "Standard gill nets",
      "cpue": 2.0
    },
    {
      "species_name": "LMB",
      "count": 49,
      "length_stats": {
        "average": null,
        "minimum": null,
        "maximum": null
      },
      "weight_stats": {
        "average": 1.27,
        "total": 28299.0,
        "quartile": "N/A"
      },
      "gear": "Standard electrofishing",
      "cpue": 82.62
    },
    {
      "species_name": "YEB",
      "count": 1,
      "length_stats": {
        "average": null,
        "minimum": null,
        "maximum": null
      },
      "weight_stats": {
        "average": 1.06,
        "total": 480.0,
        "quartile": "0.5-0.8"
      },
      "gear": "Standard trap nets",
      "cpue": 0.17
    },
    {
      "species_name": "SMB",
      "count": 2,
      "length_stats": {
        "average": null,
        "minimum": null,
        "maximum": null
      },
      "weight_stats": {
        "average": 0.0,
        "total": 0.0,
        "quartile": "N/A"
      },
      "gear": "Survey seining",
      "cpue": 1.0
    },
    {
      "species_name": "NOP",
      "count": 7,
      "length_stats": {
        "average": null,
        "minimum": null,
        "maximum": null
      },
      "weight_stats": {
        "average": 5.26,
        "total": 16708.0,
        "quartile": "N/A"
      },
      "gear": "Standard trap nets",
      "cpue": 1.17
    },
    {
      "species_name": "LMB",
      "count": 22,
      "length_stats": {
        "average": null,
        "minimum": null,
        "maximum": null
      },
      "weight_stats": {
        "average": 0.02,
        "total": 200.0,
        "quartile": "N/A"
      },
      "gear": "Survey seining",
      "cpue": 11.0
    },
    {
      "species_name": "CAP",
      "count": 6,
      "length_stats": {
        "average": null,
        "minimum": null,
        "maximum": null
      },
      "weight_stats": {
        "average": 7.28,
        "total": 19800.0,
        "quartile": "2.1-5.5"
      },
      "gear": "Standard trap nets",
      "cpue": 1.0
    },
    {
      "species_name": "BLG",
      "count": 26,
      "length_stats": {
        "average": null,
        "minimum": null,
        "maximum": null
      },
      "weight_stats": {
        "average": 0.0,
        "total": 0.0,
        "quartile": "N/A"
      },
      "gear": "Survey seining",
      "cpue": 13.0
    },
    {
      "species_name": "WAE",
      "count": 2,
      "length_stats": {
        "average": null,
        "minimum": null,
        "maximum": null
      },
      "weight_stats": {
        "average": 1.72,
        "total": 1560.0,
        "quartile": "1.1-2.9"
      },
      "gear": "Standard gill nets",
      "cpue": 1.0
    },
    {
      "species_name": "BLG",
      "count": 2,
      "length_stats": {
        "average": null,
        "minimum": null,
        "maximum": null
      },
      "weight_stats": {
        "average": 0.08,
        "total": 70.0,
        "quartile": "N/A"
      },
      "gear": "Standard gill nets",
      "cpue": 1.0
    },
    {
      "species_name": "YEP",
      "count": 21,
      "length_stats": {
        "average": null,
        "minimum": null,
        "maximum": null
      },
      "weight_stats": {
        "average": 0.02,
        "total": 190.0,
        "quartile": "N/A"
      },
      "gear": "Survey seining",
      "cpue": 10.5
    },
    {
      "species_name": "JND",
      "count": 1,
      "length_stats": {
        "average": null,
        "minimum": null,
        "maximum": null
      },
      "weight_stats": {
        "average": 0.0,
        "total": 0.0,
        "quartile": "N/A"
      },
      "gear": "Survey seining",
      "cpue": 0.5
    },
    {
      "species_name": "BIB",
      "count": 1,
      "length_stats": {
        "average": null,
        "minimum": null,
        "maximum": null
      },
      "weight_stats": {
        "average": 5.95,
        "total": 2700.0,
        "quartile": "N/A"
      },
      "gear": "Standard gill nets",
      "cpue": 0.5
    },
    {
      "species_name": "WTS",
      "count": 2,
      "length_stats": {
        "average": null,
        "minimum": null,
        "maximum": null
      },
      "weight_stats": {
        "average": 1.81,
        "total": 1640.0,
        "quartile": "1.0-2.4"
      },
      "gear": "Standard gill nets",
      "cpue": 1.0
    },
    {
      "species_name": "BLC",
      "count": 1,
      "length_stats": {
        "average": null,
        "minimum": null,
        "maximum": null
      },
      "weight_stats": {
        "average": 0.19,
        "total": 85.0,
        "quartile": "0.2-0.5"
      },
      "gear": "Standard gill nets",
      "cpue": 0.5
    },
    {
      "species_name": "BLG",
      "count": 10,
      "length_stats": {
        "average": null,
        "minimum": null,
        "maximum": null
      },
      "weight_stats": {
        "average": 0.21,
        "total": 967.0,
        "quartile": "0.1-0.3"
      },
      "gear": "Standard trap nets",
      "cpue": 1.67
    },
    {
      "species_name": "BNS",
      "count": 28,
      "length_stats": {
        "average": null,
        "minimum": null,
        "maximum": null
      },
      "weight_stats": {
        "average": 0.0,
        "total": 0.0,
        "quartile": "N/A"
      },
      "gear": "Survey seining",
      "cpue": 14.0
    },
    {
      "species_name": "NOP",
      "count": 1,
      "length_stats": {
        "average": null,
        "minimum": null,
        "maximum": null
      },
      "weight_stats": {
        "average": 0.0,
        "total": 0.0,
        "quartile": "N/A"
      },
      "gear": "Survey seining",
      "cpue": 0.5
    },
    {
      "species_name": "WTS",
      "count": 10,
      "length_stats": {
        "average": null,
        "minimum": null,
        "maximum": null
      },
      "weight_stats": {
        "average": 1.14,
        "total": 5164.0,
        "quartile": "1.1-2.4"
      },
      "gear": "Standard trap nets",
      "cpue": 1.67
    },
    {
      "species_name": "BLC",
      "count": 16,
      "length_stats": {
        "average": null,
        "minimum": null,
        "maximum": null
      },
      "weight_stats": {
        "average": 0.11,
        "total": 808.0,
        "quartile": "0.2-0.5"
      },
      "gear": "Standard trap nets",
      "cpue": 2.67
    }
  ],
  "total_fish_caught": 219,
  "dowlknum": "73007200",
  "fetch_timestamp": 1757117118.1080391
}